analysis/__init__.py
analysis/__main__.py
analysis/app.py
analysis/data/__init__.py
analysis/experiments/__init__.py
analysis/experiments/exp.py
analysis/experiments/iccd.py
analysis/experiments/plqe.py
analysis/experiments/static.py
analysis/experiments/ta.py
analysis/experiments/tcspc.py
analysis/experiments/trs.py
analysis/helpers/__init__.py
analysis/helpers/support.py
analysis/modules/__init__.py
analysis/modules/fitting.py
analysis/modules/plotting.py
analysis/tests/__init__.py
analysis/tests/unit/__init__.py
analysis/tests/unit/test_plqe.py
analysis/tests/unit/test_ta.py
analysis/tests/unit/test_ta_fitting.py
cbr_analysis-0.1.2.dist-info/LICENCE
cbr_analysis-0.1.2.dist-info/METADATA
cbr_analysis-0.1.2.dist-info/WHEEL
cbr_analysis-0.1.2.dist-info/top_level.txt
cbr_analysis-0.1.2.dist-info/RECORD
