Metadata-Version: 2.1
Name: cbr-analysis
Version: 0.1.2
Summary: OE analysis
Home-page: https://github.com/palec87/cbr-analysis/archive/v0.1.2.tar.gz
Author: DP
Author-email: david@stanka.de
License: UNKNOWN
Platform: UNKNOWN
Classifier: Programming Language :: Python :: 3
Classifier: License :: OSI Approved :: MIT License
Classifier: Operating System :: OS Independent
Requires-Python: >=3.7
Requires-Dist: numpy (==1.18.5)
Requires-Dist: h5py
Requires-Dist: pathlib
Requires-Dist: matplotlib (==3.2)
Requires-Dist: pandas
Requires-Dist: scipy
